{
  "version": 1,
  "base_track": "雨に打たれて",
  "base_artist": "Lavt",
  "createdAt": "2026-01-13T19:20:16.121824Z",
  "candidates": [
    {
      "id": "lrclib_1",
      "source": "lrclib",
      "title": "雨に打たれて",
      "artist": "Lavt",
      "has_synced": false,
      "path": "select/01_雨に打たれて_Lavt.txt"
    },
    {
      "id": "petitlyrics_1",
      "source": "petitlyrics",
      "title": "雨に打たれて",
      "artist": "Lavt",
      "has_synced": false,
      "path": "select/pl_01_雨に打たれて_Lavt.txt"
    }
  ]
}